{
  "uuid": "2609e817-f8f2-4ad2-8846-cb05bb67d047",
  "shortName": "Radium 2",
  "longName": "Radium 2 Watchface",
  "companyName": "Sterling Ely",
  "versionLabel": "2.1",
  "versionCode": 3,
  "sdkVersion": "3",
  "projectType": "native",
  "enableMultiJS": true,
  "targetPlatforms": [
    "aplite", "basalt", "chalk", "diorite", "emery", "flint", "gabbro"
  ],
  "watchapp": { "watchface": true },
  "capabilities": ["configurable", "health"],
  "messageKeys": [
    "BackgroundColor",
    "TimeTextColor",
    "DateTextColor",
    "LitHourColor",
    "LitMinuteColor",
    "LitBatteryColor",
    "LitStepsColor",
    "DimHourColor",
    "DimMinuteColor",
    "DimBatteryColor",
    "DimStepsColor",
    "OverlayBgColor",
    "StepGoal",
    "OverlayMode",
    "InvertBW",
    "ShowRing"
  ]
}
